jquants_free_mcp_server/__init__.py
jquants_free_mcp_server/server.py
jquants_free_mcp_server-0.0.1.dist-info/METADATA
jquants_free_mcp_server-0.0.1.dist-info/WHEEL
jquants_free_mcp_server-0.0.1.dist-info/entry_points.txt
jquants_free_mcp_server-0.0.1.dist-info/RECORD
