Metadata-Version: 2.4
Name: jquants-free-mcp-server
Version: 0.0.1
Summary: A MCP server project
Author-email: cygkichi <9675041+cygkichi@users.noreply.github.com>
Requires-Python: >=3.13
Requires-Dist: mcp>=1.7.1
Requires-Dist: requests>=2.32.3
